ast_error_detection/__init__.py
ast_error_detection/annotated_tree.py
ast_error_detection/convert_ast_to_custom_node.py
ast_error_detection/error_annotation.py
ast_error_detection/error_diagnosis.py
ast_error_detection/node.py
ast_error_detection/node_functions.py
ast_error_detection/zang_shasha_distance.py
asterrdetection-1.1.0.dist-info/LICENSE
asterrdetection-1.1.0.dist-info/METADATA
asterrdetection-1.1.0.dist-info/WHEEL
asterrdetection-1.1.0.dist-info/top_level.txt
asterrdetection-1.1.0.dist-info/RECORD
