Metadata-Version: 2.1
Name: asterrdetection
Version: 1.1.0
Summary: A package for finding the list of errors in a code compared to the expected code
Home-page: https://github.com/Badmavasan/ast-error-detection
Author: Badmavasan KIROUCHENASSAMY
Author-email: badmavasan.kirouchenassamy@lip6.fr
Classifier: Programming Language :: Python :: 3
Classifier: License :: OSI Approved :: GNU Affero General Public License v3
Classifier: Operating System :: OS Independent
Requires-Python: >=3.6
License-File: LICENSE
